[{"url": "https://www.kuaishou.com/short-video/3xwur3mz4nqa4xe", "title": "体育强则中国强"}, {"url": "https://www.kuaishou.com/short-video/3x36y5b3nnwyi5g", "title": "高考各地查分时间来了"}, {"url": "https://www.kuaishou.com/short-video/3x7shys8u9hdmsi", "title": "暗恋最好的答案"}, {"url": "https://www.kuaishou.com/short-video/3x8xd5m8s5ef35e", "title": "端午节假期666.7万人次出入境"}, {"url": "https://www.kuaishou.com/short-video/3xu7eszj92pmuty", "title": "热热终于等到舅舅上班带娃"}, {"url": "https://www.kuaishou.com/short-video/3x84pcc63pisuk6", "title": "多部门核查婴儿毒纸尿裤问题"}, {"url": "https://www.kuaishou.com/short-video/3xqtpr4y9xzg9ac", "title": "29岁香港女主持施可莹去世"}, {"url": "https://www.kuaishou.com/short-video/3xgjfknyw62yzka", "title": "钟美美回应入学波士顿大学"}, {"url": "https://www.kuaishou.com/short-video/3x5n4m9dy35buzg", "title": "辽宁舰编队处置日方舰机滋扰"}, {"url": "https://www.kuaishou.com/short-video/3xd938tkauqrkhu", "title": "中纪委连打两虎"}, {"url": "https://www.kuaishou.com/short-video/3xih8qnu9tyiaqu", "title": "英国首相斯塔默宣布辞职"}, {"url": "https://www.kuaishou.com/short-video/3xyihy44eqskeiq", "title": "美加墨世界杯23日赛程"}, {"url": "https://www.kuaishou.com/short-video/3xfrhypgfpw43ni", "title": "赵长鹏谈人造子宫"}, {"url": "https://www.kuaishou.com/short-video/3xy3cxgh68xqq8e", "title": "高考出分当天一定要记住这3件事"}, {"url": "https://www.kuaishou.com/short-video/3x7kz3497tks3ra", "title": "伊朗队离美前更衣室留信"}, {"url": "https://www.kuaishou.com/short-video/3x2w9vv55xt9cy4", "title": "海虾摇"}, {"url": "https://www.kuaishou.com/short-video/3x8isgtb83pndaa", "title": "恋与深空新男主"}, {"url": "https://www.kuaishou.com/short-video/3x3hp538272w3p9", "title": "中方回应侵华日军异种输血"}, {"url": "https://www.kuaishou.com/short-video/3xydtcruzrvi5hc", "title": "七仙女集体造反"}, {"url": "https://www.kuaishou.com/short-video/3xjnij643ank4vu", "title": "李太白对诗两岁萌娃"}, {"url": "https://www.kuaishou.com/short-video/3xvxcburhhvfjn4", "title": "美联储前主席格林斯潘去世"}, {"url": "https://www.kuaishou.com/short-video/3xv9n8bzzc72dbk", "title": "黑龙江绥化受损铁路通车"}, {"url": "https://www.kuaishou.com/short-video/3xmtqv87dbnnpng", "title": "陈小春为演唱会被挡观众退票"}, {"url": "https://www.kuaishou.com/short-video/3x4enfekjvm8e64", "title": "谈恋爱正确吵架方式"}, {"url": "https://www.kuaishou.com/short-video/3xfv5samt99qa8e", "title": "山西封存70年千年佛洞开放"}, {"url": "https://www.kuaishou.com/short-video/3xm3dpvrhnya49w", "title": "女子偷菜被监控喊话吓退"}, {"url": "https://www.kuaishou.com/short-video/3xvpkizbtkcbi4u", "title": "董赤赤卡点变装"}, {"url": "https://www.kuaishou.com/short-video/3xukucqynyzsxps", "title": "快手配音班集结中"}, {"url": "https://www.kuaishou.com/short-video/3xqdt8a5kbq5x7u", "title": "内蒙古自治区多地倡议禁燃"}, {"url": "https://www.kuaishou.com/short-video/3xnzcezk39yg8fk", "title": "东海部分水域实弹射击"}, {"url": "https://www.kuaishou.com/short-video/3xbbzk2jenxd6v4", "title": "送君茉莉愿君莫离"}, {"url": "https://www.kuaishou.com/short-video/3xwwmm528cmfyma", "title": "恋爱前后的双标行为"}, {"url": "https://www.kuaishou.com/short-video/3x927ymca6vihsi", "title": "我不懂赔率只懂陪你"}, {"url": "https://www.kuaishou.com/short-video/3x5zr6hvtuf5mk4", "title": "这样跟男生问好让他想你一整天"}, {"url": "https://www.kuaishou.com/short-video/3xd9vyn3ia32xhy", "title": "世界杯太会选小孩了"}, {"url": "https://www.kuaishou.com/short-video/3xkndcdzthqeg9w", "title": "毒品藏进电子烟专骗大学生"}, {"url": "https://www.kuaishou.com/short-video/3xms78qzxg8jbys", "title": "人形机器人产业再突破"}, {"url": "https://www.kuaishou.com/short-video/3xid6hhekfttnum", "title": "莫离的女性群像还是太全面了"}, {"url": "https://www.kuaishou.com/short-video/3xx6264b99npbsm", "title": "春晚机器人H1解锁新身份"}, {"url": "https://www.kuaishou.com/short-video/3xrssbh9ize34py", "title": "江西省政协原副主席尹建业被双开"}, {"url": "https://www.kuaishou.com/short-video/3xdarqyqg6yf79y", "title": "奥运冠军陈雨菲研究生毕业"}, {"url": "https://www.kuaishou.com/short-video/3xvrbtacuf77ww9", "title": "外交部回应日本逮捕电诈人员"}, {"url": "https://www.kuaishou.com/short-video/3x589mktcwg26ry", "title": "37岁工程师连轴140天猝死"}, {"url": "https://www.kuaishou.com/short-video/3x7jz5qqcvap62e", "title": "“叠滘郭富城”赛后衣服拧出水"}, {"url": "https://www.kuaishou.com/short-video/3xu4ddfjs58x4ra", "title": "佛得角本土球员月薪不足两千"}, {"url": "https://www.kuaishou.com/short-video/3xs4qnecp4kibuy", "title": "何小鹏任蚂蚁集团独董"}, {"url": "https://www.kuaishou.com/short-video/3xq6mb87ph4rn92", "title": "超自然鬼吹灯联动云南虫谷"}, {"url": "https://www.kuaishou.com/short-video/3xujfmgspppgksw", "title": "三角洲S10刀皮北极星黑海返场"}, {"url": "https://www.kuaishou.com/short-video/3xsjr9b9z5bcvje", "title": "印度或迎史上最大IPO"}, {"url": "https://www.kuaishou.com/short-video/3xv7vebfahy9e7i", "title": "假黄精系洋姜山药冒充"}, {"url": "https://www.kuaishou.com/short-video/3xiy3zkbq7viksi", "title": "得罪千百人 不负十四亿"}, {"url": "https://www.kuaishou.com/short-video/3x7529qqcehzk74", "title": "多部门核查婴儿毒纸尿裤问题"}, {"url": "https://www.kuaishou.com/short-video/3xw5qhfc2asm4j4", "title": "中方回应侵华日军异种输血"}, {"url": "https://www.kuaishou.com/short-video/3xjv86ic9nbj9t9", "title": "29岁香港女主持施可莹去世"}, {"url": "https://www.kuaishou.com/short-video/3xibyr6zqf9m5xc", "title": "英国首相斯塔默宣布辞职"}, {"url": "https://www.kuaishou.com/short-video/3xdzwqpau6vfm7m", "title": "广西运镜萌宠版"}, {"url": "https://www.kuaishou.com/short-video/3xu9tpzwnnx8dvy", "title": "辽宁舰应对日方危险行径"}, {"url": "https://www.kuaishou.com/short-video/3xcb2bc4pd7cipc", "title": "外交部回应日本逮捕电诈人员"}, {"url": "https://www.kuaishou.com/short-video/3x9mshyzft756nk", "title": "全球资本看好中国资产"}, {"url": "https://www.kuaishou.com/short-video/3xmkxdc4izg2zkq", "title": "村民辟谣猎德龙舟要验资上船"}, {"url": "https://www.kuaishou.com/short-video/3xjehzuy8db4m4w", "title": "中考最后十五分钟回望初中三年"}, {"url": "https://www.kuaishou.com/short-video/3x4gmu5duy3dytk", "title": "陈小春为演唱会被挡观众退票"}, {"url": "https://www.kuaishou.com/short-video/3xqpap6jxrdyfee", "title": "男子带90岁父亲看龙舟"}, {"url": "https://www.kuaishou.com/short-video/3xcs7wt45pmfrs2", "title": "陈丽君我的大观园合肥落幕"}, {"url": "https://www.kuaishou.com/short-video/3x3g78ctbr6zbea", "title": "问心2小睿被送到医院"}, {"url": "https://www.kuaishou.com/short-video/3xaz7g9kxep5wt9", "title": "灵境行者新pv上线"}, {"url": "https://www.kuaishou.com/short-video/3xhzyctrafe3zdg", "title": "中方望立陶宛纠正错误"}, {"url": "https://www.kuaishou.com/short-video/3x9venxv9f72g2y", "title": "东海部分水域实弹射击"}, {"url": "https://www.kuaishou.com/short-video/3xkxsgpq4jee3xe", "title": "雪中悍刀行新pv上线"}, {"url": "https://www.kuaishou.com/short-video/3xf2hwyk2jrxb8c", "title": "台风米克拉对上海暂无直接影响"}, {"url": "https://www.kuaishou.com/short-video/3xd6bt99dijr3hu", "title": "猫咪气势拉满战斗力为零"}, {"url": "https://www.kuaishou.com/short-video/3x8dy2ts3y7x9sg", "title": "滴露就争议广告致歉"}, {"url": "https://www.kuaishou.com/short-video/3xkq4cnmzihqzgk", "title": "五年级男孩身高1米87"}, {"url": "https://www.kuaishou.com/short-video/3xx8su8ycuimpes", "title": "中国曾拒加G7"}, {"url": "https://www.kuaishou.com/short-video/3xywu9tnt7879su", "title": "还有什么是李蠕蠕模仿不了的"}, {"url": "https://www.kuaishou.com/short-video/3xv6vewduapj5wi", "title": "太原中考巨型向日葵抢镜"}, {"url": "https://www.kuaishou.com/short-video/3xcvfk6k8yxjbf4", "title": "潘阳父亲节花式套路潘长江"}, {"url": "https://www.kuaishou.com/short-video/3xyhffdke6mpsuc", "title": "癌症芯片先驱陈伟强回国"}, {"url": "https://www.kuaishou.com/short-video/3x47k7x7iucugne", "title": "外交部批日本“再军事化”"}, {"url": "https://www.kuaishou.com/short-video/3x5g5bbmkqwbe7c", "title": "A股三大指数集体大涨"}, {"url": "https://www.kuaishou.com/short-video/3xu3ufqbtqvfi6k", "title": "这就是满级干饭孩"}, {"url": "https://www.kuaishou.com/short-video/3xw833s57cscjeq", "title": "大学老师炫耀帮学生考研上岸"}, {"url": "https://www.kuaishou.com/short-video/3xztmi4wwp83b5q", "title": "白玉兰获奖名单预测"}, {"url": "https://www.kuaishou.com/short-video/3xiybnbk59x8uqw", "title": "北京公寓销售骗租警方介入"}, {"url": "https://www.kuaishou.com/short-video/3x2qzkjfhjbrges", "title": "乌拉圭2比2佛得角"}, {"url": "https://www.kuaishou.com/short-video/3xy542kaf4jmiyw", "title": "安徽女子发明电饭煲扣粽"}, {"url": "https://www.kuaishou.com/short-video/3x9ardt24h5czvs", "title": "良子公布与助理恋情"}, {"url": "https://www.kuaishou.com/short-video/3x23sr4cvwffc4u", "title": "我国将建立房屋统一代码"}, {"url": "https://www.kuaishou.com/short-video/3x8b8b4etkk2cj9", "title": "曝乌兰图雅自己对接工作和商务"}, {"url": "https://www.kuaishou.com/short-video/3xrza78qseegbdq", "title": "赵云孙权姬小满新皮肤CG上线"}, {"url": "https://www.kuaishou.com/short-video/3xkyrhqmen24r62", "title": "从“六项规定”到“八项规定”"}, {"url": "https://www.kuaishou.com/short-video/3xjc2gd5pefnbae", "title": "教你使用高考志愿填报官方工具"}, {"url": "https://www.kuaishou.com/short-video/3xsa2ha3xd4e4sy", "title": "演员李现为世界杯开球"}, {"url": "https://www.kuaishou.com/short-video/3x5j38w4grr8up6", "title": "半导体板块遭多路资金集体兑现"}, {"url": "https://www.kuaishou.com/short-video/3xmdkk7uj666f62", "title": "苹果折叠屏或于9月发布"}, {"url": "https://www.kuaishou.com/short-video/3xy2a7wfwprwrim", "title": "佛得角门将收到不续约通知"}, {"url": "https://www.kuaishou.com/short-video/3x9syvrezvaj9sc", "title": "著名考古学家任式楠病逝"}, {"url": "https://www.kuaishou.com/short-video/3xqcd8vhi3zwsai", "title": "蒙超赛场啦啦操活力四射"}, {"url": "https://www.kuaishou.com/short-video/3xf7e7vn4y243h2", "title": "女儿点燃野草父亲扑火身亡"}, {"url": "https://www.kuaishou.com/short-video/3xtq9npztbjeina", "title": "油价拉升黄金白银走低"}, {"url": "https://www.kuaishou.com/short-video/3x98xfbcvgitiim", "title": "天赐父亲称不会麻烦大女儿"}, {"url": "https://www.kuaishou.com/short-video/3xg7h3qvee8gs5a", "title": "佛得角逼平两个世界冠军"}, {"url": "https://www.kuaishou.com/short-video/3xqkhhe5xihiyfw", "title": "乌拉圭门将超巨失误"}, {"url": "https://www.kuaishou.com/short-video/3xg67c8zzyhkpb6", "title": "秦腔艺术家李梅看主角大哭"}, {"url": "https://www.kuaishou.com/short-video/3xgkz7t34j8i359", "title": "67岁生女母亲脑梗入院"}, {"url": "https://www.kuaishou.com/short-video/3x97ptqdm8zt73w", "title": "长春中考时间确定"}, {"url": "https://www.kuaishou.com/short-video/3xfiyp9gzuz75mk", "title": "西班牙4比0大胜沙特"}, {"url": "https://www.kuaishou.com/short-video/3xiw46dxjtj4x4k", "title": "油价最新调整通知"}, {"url": "https://www.kuaishou.com/short-video/3xwq7dxvhjgdfju", "title": "我要吃回属于我的一切"}, {"url": "https://www.kuaishou.com/short-video/3xmyja8uqs7ggh9", "title": "老外都在问为什么中国没去世界杯"}, {"url": "https://www.kuaishou.com/short-video/3x3m7at3qnqiiek", "title": "小米高管回应雷军过早摆拍争议"}, {"url": "https://www.kuaishou.com/short-video/3xium3mkyqq7hmu", "title": "德国重炮弗林斯入驻快手"}, {"url": "https://www.kuaishou.com/short-video/3xpjej297qijnp2", "title": "猪肾移植猴存活超600天"}, {"url": "https://www.kuaishou.com/short-video/3xy7nmeiupk2y66", "title": "吴宜泽回应夺冠全凭运气"}, {"url": "https://www.kuaishou.com/short-video/3x4hebmci4u8mms", "title": "印度破获跨邦婴儿贩卖案"}, {"url": "https://www.kuaishou.com/short-video/3xs4mbvz3dnsiwy", "title": "呼和浩特中考出行攻略"}, {"url": "https://www.kuaishou.com/short-video/3xrubd83jng5dis", "title": "挪威战机伴飞监视俄侦察机"}, {"url": "https://www.kuaishou.com/short-video/3xnav9u8nkcmxzi", "title": "张雨霏遗憾无自己的单项世界纪录"}, {"url": "https://www.kuaishou.com/short-video/3xs8wbfxi7mh95a", "title": "义乌迷你足球月销40万件"}, {"url": "https://www.kuaishou.com/short-video/3xffp5c6gw9k8py", "title": "巴基斯坦防长强硬警告印度"}, {"url": "https://www.kuaishou.com/short-video/3xni26appyi548g", "title": "佛得角世界杯首粒进球"}, {"url": "https://www.kuaishou.com/short-video/3xp5ens3xz86ju2", "title": "政府采购拉黑46家美企"}, {"url": "https://www.kuaishou.com/short-video/3xkdnb3wjfcueb4", "title": "北京今日大部分地区有雷阵雨"}, {"url": "https://www.kuaishou.com/short-video/3xavh4g8zcgrw82", "title": "盘锦设东北超第二现场"}, {"url": "https://www.kuaishou.com/short-video/3x6d7mxt9sezgby", "title": "博主用龙虾手搓大力神杯"}, {"url": "https://www.kuaishou.com/short-video/3xm3jb34dr7szdm", "title": "凤凰传奇广州演唱会太燃了"}, {"url": "https://www.kuaishou.com/short-video/3xxuz374eb8bb8m", "title": "檀健次空耳把非总听成飞走"}, {"url": "https://www.kuaishou.com/short-video/3xap2fs2dqa8m3s", "title": "山东一河道现严重黑臭污染"}, {"url": "https://www.kuaishou.com/short-video/3xsu3xywz5kw3mu", "title": "渐冻症女子遭猥亵案宣判"}, {"url": "https://www.kuaishou.com/short-video/3xsdnswqye6cwy6", "title": "首台630℃煤电机组投运"}, {"url": "https://www.kuaishou.com/short-video/3x9eh4ssxdre2z4", "title": "妻子做丰盛大餐犒劳丈夫"}, {"url": "https://www.kuaishou.com/short-video/3xraw4yasa37u5a", "title": "黄仁勋赞中国是科技中心"}, {"url": "https://www.kuaishou.com/short-video/3x85r57uphpzqre", "title": "太久没穿的鞋比桃酥还酥"}, {"url": "https://www.kuaishou.com/short-video/3xjjpwdxvgavuum", "title": "张韶涵把雨衣穿成高定"}]